test_InvokeMcpServer.py
InvokeMcpServer/InvokeMcpServer.py
InvokeMcpServer/LoadMcpServerConfig.py
InvokeMcpServer/__init__.py
invokemcpserver-0.1.6.dist-info/METADATA
invokemcpserver-0.1.6.dist-info/WHEEL
invokemcpserver-0.1.6.dist-info/top_level.txt
invokemcpserver-0.1.6.dist-info/RECORD
